{
  "main": {
    "name":"Aaron Feingold",
    "occupation":"Software Engineer",
    "description":"I make apps for people with an appetite",
    "image":"profilepic.jpg",
    "bio":"Guitarist. Griller. Great Guy, yano, what else should be said? Oh yeah...a junior dev by day, and a student by night. Someone who's willing to put their time into understanding the ins and outs of web development to solve the many problems of the world. Especially those which concern the environment, the economy, the...",
    "contactmessage":"Here is where you should write your message to readers to have them get in contact with you.",
    "email": "ajfeingold88@gmail.com",
    "phone": "555-555-5555",
    "address":{
      "street":"2208 Cadiz St.",
      "city":"New Orleans",
      "state":"LA",
      "zip": "70115"
    },
    "website": "https://a-feingold.medium.com/",
    "resumeDownload":"https://docs.google.com/document/d/e/2PACX-1vRaI0e3eCvTCFZKI0IEmEjJr6FhmhtZSvIgzugUV4SQuMZ5jPNjGR2eAY13v2eCIj1ZvjBPkdwH9vv7/pub",
    "social":[
      {
        "name":"linkedin",
        "url":"https://www.linkedin.com/in/aaron-feingold/",
        "className":"fa fa-linkedin"
      },
      {
        "name":"github",
        "url":"https://github.com/aaronfeingold",
        "className":"fa fa-github"
      }
    ]
  },
  "resume":{
    "skillmessage":"Messing with AWS, Docker, Linux, MERN, Python, that's the highlight. Percentage likeliness to be used on any given day in bar form for fun, why not?: ",
    "education":[
      {
        "school":"The Flatiron School",
        "url":"https://flatironschool.com/",
        "degree":"Software Engineering",
        "graduated":"November 2020",
        "description":"RoR and React. Prog Web Sites. "
      },
      {
        "school":"Tulane University",
        "degree":"Political Science and Latin American Studies",
        "graduated":"April 2010",
        "description":"College was fun, very fun"
      }
    ],
    "work":[
      {
        "company":"Republic National Distributing Company",
        "title":"On-Premise Sales Representative",
        "years":"April 2015 - May 2020",
        "description":"Selling wine full time."
      }
    ],
    "skills":[
      {
        "name":"reactjs",
        "className":"fa fa-linkedin",
        "desc":"JavaScript/Type-Script",
        "level":"100%"
      },
      {
        "name":"git",
        "desc":"Git/GitLab/GitHub",
        "level":"100%"
      },
      {
        "name":"reactjs",
        "desc":"React-Redux/JSX/TSX",
        "level":"90%"
      },
      {
        "name":"nodejs",
        "desc":"NodeJS/ExpressJS",
        "level":"80%"
      },
      {
        "name":"mongo",
        "desc":"MongoDB/Atlas",
        "level":"80%"
      },
      {
        "name":"linux",
        "desc":"Linux/ARCH/Ubuntu/RedHat",
        "level":"80%"
      }
    ]
  },
  "portfolio":{
    "projects": [
      {
        "title":"Prepped Nola",
        "category":"Kitchen Fatigue? Use this app to build weekly meal plans, and save time and engergy",
        "image":"prepped-nola-screenshot.jpg",
        "url":"https://meals-prepped-nola.netlify.app"
      },
      {
        "title":"My_Winery",
        "category":"Too many barrels in the cellar? Use this to decide what needs to get bottled asap",
        "image":"my-winery-screenshot.jpg",
        "url":"https://my-winery-1.herokuapp.com/"
      }
    ]
  }
}
